contactapi/__init__.py
contactapi/__main__.py
contactapi/config.py
contactapi/crud.py
contactapi/main.py
contactapi/models.py
contactapi/router.py
contactapi/schemas.py
contactapi-0.0.24.dist-info/METADATA
contactapi-0.0.24.dist-info/WHEEL
contactapi-0.0.24.dist-info/entry_points.txt
contactapi-0.0.24.dist-info/top_level.txt
contactapi-0.0.24.dist-info/RECORD
