Metadata-Version: 2.1
Name: contactapi
Version: 0.0.24
Summary: Just a demo project
Keywords: fastapi,project
Requires-Python: >=3.10
Requires-Dist: fastapi
Requires-Dist: uvicorn
Requires-Dist: sqlalchemy
